{
  "frames": {
    "enemies-archer-archer-spritesheet-with-shadow_000": {
      "frame": {
        "x": 11,
        "y": 13,
        "w": 11,
        "h": 16
      },
      "spriteSourceSize": {
        "x": 0,
        "y": 0,
        "w": 11,
        "h": 16
      },
      "sourceSize": {
        "w": 11,
        "h": 16
      }
    },
    "enemies-archer-archer-spritesheet-with-shadow_001": {
      "frame": {
        "x": 43,
        "y": 12,
        "w": 11,
        "h": 17
      },
      "spriteSourceSize": {
        "x": 0,
        "y": 0,
        "w": 11,
        "h": 17
      },
      "sourceSize": {
        "w": 11,
        "h": 17
      }
    },
    "enemies-archer-archer-spritesheet-with-shadow_002": {
      "frame": {
        "x": 75,
        "y": 12,
        "w": 11,
        "h": 17
      },
      "spriteSourceSize": {
        "x": 0,
        "y": 0,
        "w": 11,
        "h": 17
      },
      "sourceSize": {
        "w": 11,
        "h": 17
      }
    },
    "enemies-archer-archer-spritesheet-with-shadow_003": {
      "frame": {
        "x": 107,
        "y": 13,
        "w": 11,
        "h": 16
      },
      "spriteSourceSize": {
        "x": 0,
        "y": 0,
        "w": 11,
        "h": 16
      },
      "sourceSize": {
        "w": 11,
        "h": 16
      }
    },
    "enemies-archer-archer-spritesheet-with-shadow_004": {
      "frame": {
        "x": 139,
        "y": 14,
        "w": 11,
        "h": 15
      },
      "spriteSourceSize": {
        "x": 0,
        "y": 0,
        "w": 11,
        "h": 15
      },
      "sourceSize": {
        "w": 11,
        "h": 15
      }
    },
    "enemies-archer-archer-spritesheet-with-shadow_005": {
      "frame": {
        "x": 10,
        "y": 47,
        "w": 13,
        "h": 14
      },
      "spriteSourceSize": {
        "x": 0,
        "y": 0,
        "w": 13,
        "h": 14
      },
      "sourceSize": {
        "w": 13,
        "h": 14
      }
    },
    "enemies-archer-archer-spritesheet-with-shadow_006": {
      "frame": {
        "x": 43,
        "y": 45,
        "w": 11,
        "h": 16
      },
      "spriteSourceSize": {
        "x": 0,
        "y": 0,
        "w": 11,
        "h": 16
      },
      "sourceSize": {
        "w": 11,
        "h": 16
      }
    },
    "enemies-archer-archer-spritesheet-with-shadow_007": {
      "frame": {
        "x": 75,
        "y": 44,
        "w": 10,
        "h": 17
      },
      "spriteSourceSize": {
        "x": 0,
        "y": 0,
        "w": 10,
        "h": 17
      },
      "sourceSize": {
        "w": 10,
        "h": 17
      }
    },
    "enemies-archer-archer-spritesheet-with-shadow_008": {
      "frame": {
        "x": 107,
        "y": 45,
        "w": 11,
        "h": 16
      },
      "spriteSourceSize": {
        "x": 0,
        "y": 0,
        "w": 11,
        "h": 16
      },
      "sourceSize": {
        "w": 11,
        "h": 16
      }
    },
    "enemies-archer-archer-spritesheet-with-shadow_009": {
      "frame": {
        "x": 11,
        "y": 76,
        "w": 11,
        "h": 17
      },
      "spriteSourceSize": {
        "x": 0,
        "y": 0,
        "w": 11,
        "h": 17
      },
      "sourceSize": {
        "w": 11,
        "h": 17
      }
    },
    "enemies-archer-archer-spritesheet-with-shadow_010": {
      "frame": {
        "x": 43,
        "y": 78,
        "w": 11,
        "h": 15
      },
      "spriteSourceSize": {
        "x": 0,
        "y": 0,
        "w": 11,
        "h": 15
      },
      "sourceSize": {
        "w": 11,
        "h": 15
      }
    },
    "enemies-archer-archer-spritesheet-with-shadow_011": {
      "frame": {
        "x": 75,
        "y": 77,
        "w": 11,
        "h": 16
      },
      "spriteSourceSize": {
        "x": 0,
        "y": 0,
        "w": 11,
        "h": 16
      },
      "sourceSize": {
        "w": 11,
        "h": 16
      }
    },
    "enemies-archer-archer-spritesheet-with-shadow_012": {
      "frame": {
        "x": 107,
        "y": 78,
        "w": 11,
        "h": 15
      },
      "spriteSourceSize": {
        "x": 0,
        "y": 0,
        "w": 11,
        "h": 15
      },
      "sourceSize": {
        "w": 11,
        "h": 15
      }
    },
    "enemies-archer-archer-spritesheet-with-shadow_013": {
      "frame": {
        "x": 139,
        "y": 78,
        "w": 11,
        "h": 15
      },
      "spriteSourceSize": {
        "x": 0,
        "y": 0,
        "w": 11,
        "h": 15
      },
      "sourceSize": {
        "w": 11,
        "h": 15
      }
    },
    "enemies-archer-archer-spritesheet-with-shadow_014": {
      "frame": {
        "x": 171,
        "y": 78,
        "w": 11,
        "h": 15
      },
      "spriteSourceSize": {
        "x": 0,
        "y": 0,
        "w": 11,
        "h": 15
      },
      "sourceSize": {
        "w": 11,
        "h": 15
      }
    },
    "enemies-archer-archer-spritesheet-with-shadow_015": {
      "frame": {
        "x": 203,
        "y": 77,
        "w": 11,
        "h": 16
      },
      "spriteSourceSize": {
        "x": 0,
        "y": 0,
        "w": 11,
        "h": 16
      },
      "sourceSize": {
        "w": 11,
        "h": 16
      }
    },
    "enemies-archer-archer-spritesheet-with-shadow_016": {
      "frame": {
        "x": 11,
        "y": 108,
        "w": 11,
        "h": 17
      },
      "spriteSourceSize": {
        "x": 0,
        "y": 0,
        "w": 11,
        "h": 17
      },
      "sourceSize": {
        "w": 11,
        "h": 17
      }
    },
    "enemies-archer-archer-spritesheet-with-shadow_017": {
      "frame": {
        "x": 43,
        "y": 108,
        "w": 11,
        "h": 17
      },
      "spriteSourceSize": {
        "x": 0,
        "y": 0,
        "w": 11,
        "h": 17
      },
      "sourceSize": {
        "w": 11,
        "h": 17
      }
    },
    "enemies-archer-archer-spritesheet-with-shadow_018": {
      "frame": {
        "x": 7,
        "y": 139,
        "w": 18,
        "h": 16
      },
      "spriteSourceSize": {
        "x": 0,
        "y": 0,
        "w": 18,
        "h": 16
      },
      "sourceSize": {
        "w": 18,
        "h": 16
      }
    },
    "enemies-archer-archer-spritesheet-with-shadow_019": {
      "frame": {
        "x": 19,
        "y": 138,
        "w": 4,
        "h": 4
      },
      "spriteSourceSize": {
        "x": 0,
        "y": 0,
        "w": 4,
        "h": 4
      },
      "sourceSize": {
        "w": 4,
        "h": 4
      }
    },
    "enemies-archer-archer-spritesheet-with-shadow_020": {
      "frame": {
        "x": 40,
        "y": 141,
        "w": 4,
        "h": 5
      },
      "spriteSourceSize": {
        "x": 0,
        "y": 0,
        "w": 4,
        "h": 5
      },
      "sourceSize": {
        "w": 4,
        "h": 5
      }
    },
    "enemies-archer-archer-spritesheet-with-shadow_021": {
      "frame": {
        "x": 46,
        "y": 138,
        "w": 5,
        "h": 9
      },
      "spriteSourceSize": {
        "x": 0,
        "y": 0,
        "w": 5,
        "h": 9
      },
      "sourceSize": {
        "w": 5,
        "h": 9
      }
    },
    "enemies-archer-archer-spritesheet-with-shadow_022": {
      "frame": {
        "x": 52,
        "y": 137,
        "w": 4,
        "h": 3
      },
      "spriteSourceSize": {
        "x": 0,
        "y": 0,
        "w": 4,
        "h": 3
      },
      "sourceSize": {
        "w": 4,
        "h": 3
      }
    },
    "enemies-archer-archer-spritesheet-with-shadow_023": {
      "frame": {
        "x": 53,
        "y": 142,
        "w": 4,
        "h": 6
      },
      "spriteSourceSize": {
        "x": 0,
        "y": 0,
        "w": 4,
        "h": 6
      },
      "sourceSize": {
        "w": 4,
        "h": 6
      }
    },
    "enemies-archer-archer-spritesheet-with-shadow_024": {
      "frame": {
        "x": 78,
        "y": 136,
        "w": 5,
        "h": 5
      },
      "spriteSourceSize": {
        "x": 0,
        "y": 0,
        "w": 5,
        "h": 5
      },
      "sourceSize": {
        "w": 5,
        "h": 5
      }
    },
    "enemies-archer-archer-spritesheet-with-shadow_025": {
      "frame": {
        "x": 110,
        "y": 138,
        "w": 5,
        "h": 5
      },
      "spriteSourceSize": {
        "x": 0,
        "y": 0,
        "w": 5,
        "h": 5
      },
      "sourceSize": {
        "w": 5,
        "h": 5
      }
    },
    "enemies-archer-archer-spritesheet-with-shadow_026": {
      "frame": {
        "x": 38,
        "y": 148,
        "w": 6,
        "h": 6
      },
      "spriteSourceSize": {
        "x": 0,
        "y": 0,
        "w": 6,
        "h": 6
      },
      "sourceSize": {
        "w": 6,
        "h": 6
      }
    },
    "enemies-archer-archer-spritesheet-with-shadow_027": {
      "frame": {
        "x": 45,
        "y": 150,
        "w": 5,
        "h": 5
      },
      "spriteSourceSize": {
        "x": 0,
        "y": 0,
        "w": 5,
        "h": 5
      },
      "sourceSize": {
        "w": 5,
        "h": 5
      }
    },
    "enemies-archer-archer-spritesheet-with-shadow_028": {
      "frame": {
        "x": 55,
        "y": 148,
        "w": 3,
        "h": 4
      },
      "spriteSourceSize": {
        "x": 0,
        "y": 0,
        "w": 3,
        "h": 4
      },
      "sourceSize": {
        "w": 3,
        "h": 4
      }
    },
    "enemies-archer-archer-spritesheet-with-shadow_029": {
      "frame": {
        "x": 142,
        "y": 145,
        "w": 5,
        "h": 5
      },
      "spriteSourceSize": {
        "x": 0,
        "y": 0,
        "w": 5,
        "h": 5
      },
      "sourceSize": {
        "w": 5,
        "h": 5
      }
    },
    "enemies-archer-archer-spritesheet-with-shadow_030": {
      "frame": {
        "x": 173,
        "y": 150,
        "w": 7,
        "h": 6
      },
      "spriteSourceSize": {
        "x": 0,
        "y": 0,
        "w": 7,
        "h": 6
      },
      "sourceSize": {
        "w": 7,
        "h": 6
      }
    },
    "enemies-archer-archer-spritesheet-with-shadow_031": {
      "frame": {
        "x": 205,
        "y": 149,
        "w": 7,
        "h": 7
      },
      "spriteSourceSize": {
        "x": 0,
        "y": 0,
        "w": 7,
        "h": 7
      },
      "sourceSize": {
        "w": 7,
        "h": 7
      }
    },
    "enemies-archer-archer-spritesheet-with-shadow_032": {
      "frame": {
        "x": 237,
        "y": 150,
        "w": 7,
        "h": 6
      },
      "spriteSourceSize": {
        "x": 0,
        "y": 0,
        "w": 7,
        "h": 6
      },
      "sourceSize": {
        "w": 7,
        "h": 6
      }
    },
    "enemies-archer-archer-spritesheet-with-shadow_033": {
      "frame": {
        "x": 143,
        "y": 153,
        "w": 5,
        "h": 2
      },
      "spriteSourceSize": {
        "x": 0,
        "y": 0,
        "w": 5,
        "h": 2
      },
      "sourceSize": {
        "w": 5,
        "h": 2
      }
    }
  },
  "meta": {
    "image": "enemies-archer-archer-spritesheet-with-shadow.png",
    "size": {
      "w": 256,
      "h": 160
    },
    "scale": 1,
    "mode": "flood",
    "sourcePath": "01 Stranded - Starter Pack v1.1/Enemies/Archer/Archer spritesheet with shadow.png"
  }
}